setup.py
aautilitypackage.egg-info/PKG-INFO
aautilitypackage.egg-info/SOURCES.txt
aautilitypackage.egg-info/dependency_links.txt
aautilitypackage.egg-info/not-zip-safe
aautilitypackage.egg-info/top_level.txt
aautilitypkg/__init__.py