Metadata-Version: 1.0
Name: aautilitypackage
Version: 0.2
Summary: Utility functions
Home-page: UNKNOWN
Author: Gaurav Sharma
Author-email: gauravdbdev@gmail.com
License: MIT
Platform: UNKNOWN
